{
  "configVersion": "1.2.0",

  "components": [
    {
      "name": "default",
      "includePaths": [
        "app/",
        "resources/"
      ],
      "excludePaths": [],
      "translationFileName": "resources/lang/i18n/{localeName}/LC_MESSAGES/default.po"
    }
  ],

  "vcs": "bitbucket",
  "vcsUsername": "lehadnk@test.com",
  "vcsPassword": "password",
  "vcsRepository": "lehadnk/crm",

  "translationBranchName": "translation",

  "weblateServiceUrl": "http://weblate.test.com",
  "weblateProjectSlug": "crm",
  "weblateComponentSlug": "main",
  "weblateAuthToken": "token",

  "outputJson": false
}
